ntc_rosetta_conf/__init__.py
ntc_rosetta_conf/cmd.py
ntc_rosetta_conf/server.py
ntc_rosetta_conf/usr_conf_data_handlers.py
ntc_rosetta_conf/usr_datastore.py
ntc_rosetta_conf/usr_op_handlers.py
ntc_rosetta_conf/usr_state_data_handlers.py
ntc_rosetta_conf/yang/ietf-yang-library.yang
ntc_rosetta_conf/yang/ntc-rosetta-conf.yang
ntc_rosetta_conf-0.1.0.dist-info/entry_points.txt
ntc_rosetta_conf-0.1.0.dist-info/WHEEL
ntc_rosetta_conf-0.1.0.dist-info/METADATA
ntc_rosetta_conf-0.1.0.dist-info/RECORD
